{
  "articles": [
    {
      "title": "Наикрутейший заголовок",
      "author": "Суперский автор",
      "source": "Супер секретный источник",
      "coverImage": "https://s1.1zoom.ru/big0/367/433183-Kysb.jpg",
      "description": "Lorem ipsum dolor sit amet, consectetur adipiscing elit. Integer vehicula lectus ut massa finibus interdum. Sed tincidunt felis eget purus pulvinar, at condimentum metus sodales. Praesent dictum commodo nunc, ut ornare metus gravida eget.",
      "content": {
        "time": 1634424774054,
        "blocks": [
          {
            "id": "Ik8uWoec7B",
            "type": "header",
            "data": {
              "text": "Заголовок",
              "level": 2
            }
          },
          {
            "id": "VggAl6ZV9M",
            "type": "paragraph",
            "data": {
              "text": "Текст текст текст"
            }
          },
          {
            "id": "3GICv7RT3x",
            "type": "list",
            "data": {
              "style": "ordered",
              "items": ["список 1", "список 2", "список 3"]
            }
          }
        ],
        "version": "2.22.2"
      },
      "id": 1
    },
    {
      "title": "Наикрутейший заголовок",
      "author": "Суперский автор",
      "source": "Супер секретный источник",
      "coverImage": "https://s1.1zoom.ru/big0/367/433183-Kysb.jpg",
      "description": "Lorem ipsum dolor sit amet, consectetur adipiscing elit. Integer vehicula lectus ut massa finibus interdum. Sed tincidunt felis eget purus pulvinar, at condimentum metus sodales. Praesent dictum commodo nunc, ut ornare metus gravida eget.",
      "content": {
        "time": 1634424774054,
        "blocks": [
          {
            "id": "Ik8uWoec7B",
            "type": "header",
            "data": {
              "text": "Заголовок",
              "level": 2
            }
          },
          {
            "id": "VggAl6ZV9M",
            "type": "paragraph",
            "data": {
              "text": "Текст текст текст"
            }
          },
          {
            "id": "3GICv7RT3x",
            "type": "list",
            "data": {
              "style": "ordered",
              "items": ["список 1", "список 2", "список 3"]
            }
          }
        ],
        "version": "2.22.2"
      },
      "id": 2
    },
    {
      "title": "Наикрутейший заголовок",
      "author": "Суперский автор",
      "source": "Супер секретный источник",
      "coverImage": "https://s1.1zoom.ru/big0/367/433183-Kysb.jpg",
      "description": "Lorem ipsum dolor sit amet, consectetur adipiscing elit. Integer vehicula lectus ut massa finibus interdum. Sed tincidunt felis eget purus pulvinar, at condimentum metus sodales. Praesent dictum commodo nunc, ut ornare metus gravida eget.",
      "content": {
        "time": 1634424774054,
        "blocks": [
          {
            "id": "Ik8uWoec7B",
            "type": "header",
            "data": {
              "text": "Заголовок",
              "level": 2
            }
          },
          {
            "id": "VggAl6ZV9M",
            "type": "paragraph",
            "data": {
              "text": "Текст текст текст"
            }
          },
          {
            "id": "3GICv7RT3x",
            "type": "list",
            "data": {
              "style": "ordered",
              "items": ["список 1", "список 2", "список 3"]
            }
          }
        ],
        "version": "2.22.2"
      },
      "id": 3
    },
    {
      "title": "Наикрутейший заголовок",
      "author": "Суперский автор",
      "source": "Супер секретный источник",
      "coverImage": "https://s1.1zoom.ru/big0/367/433183-Kysb.jpg",
      "description": "Lorem ipsum dolor sit amet, consectetur adipiscing elit. Integer vehicula lectus ut massa finibus interdum. Sed tincidunt felis eget purus pulvinar, at condimentum metus sodales. Praesent dictum commodo nunc, ut ornare metus gravida eget.",
      "content": {
        "time": 1634424774054,
        "blocks": [
          {
            "id": "Ik8uWoec7B",
            "type": "header",
            "data": {
              "text": "Заголовок",
              "level": 2
            }
          },
          {
            "id": "VggAl6ZV9M",
            "type": "paragraph",
            "data": {
              "text": "Текст текст текст"
            }
          },
          {
            "id": "3GICv7RT3x",
            "type": "list",
            "data": {
              "style": "ordered",
              "items": ["список 1", "список 2", "список 3"]
            }
          }
        ],
        "version": "2.22.2"
      },
      "id": 4
    },
    {
      "title": "Наикрутейший заголовок",
      "author": "Суперский автор",
      "source": "Супер секретный источник",
      "coverImage": "https://s1.1zoom.ru/big0/367/433183-Kysb.jpg",
      "description": "Lorem ipsum dolor sit amet, consectetur adipiscing elit. Integer vehicula lectus ut massa finibus interdum. Sed tincidunt felis eget purus pulvinar, at condimentum metus sodales. Praesent dictum commodo nunc, ut ornare metus gravida eget.",
      "content": {
        "time": 1634424774054,
        "blocks": [
          {
            "id": "Ik8uWoec7B",
            "type": "header",
            "data": {
              "text": "Заголовок",
              "level": 2
            }
          },
          {
            "id": "VggAl6ZV9M",
            "type": "paragraph",
            "data": {
              "text": "Текст текст текст"
            }
          },
          {
            "id": "3GICv7RT3x",
            "type": "list",
            "data": {
              "style": "ordered",
              "items": ["список 1", "список 2", "список 3"]
            }
          }
        ],
        "version": "2.22.2"
      },
      "id": 5
    },
    {
      "title": "Наикрутейший заголовок",
      "author": "Суперский автор",
      "source": "Супер секретный источник",
      "coverImage": "https://s1.1zoom.ru/big0/367/433183-Kysb.jpg",
      "description": "Lorem ipsum dolor sit amet, consectetur adipiscing elit. Integer vehicula lectus ut massa finibus interdum. Sed tincidunt felis eget purus pulvinar, at condimentum metus sodales. Praesent dictum commodo nunc, ut ornare metus gravida eget.",
      "content": {
        "time": 1634424774054,
        "blocks": [
          {
            "id": "Ik8uWoec7B",
            "type": "header",
            "data": {
              "text": "Заголовок",
              "level": 2
            }
          },
          {
            "id": "VggAl6ZV9M",
            "type": "paragraph",
            "data": {
              "text": "Текст текст текст"
            }
          },
          {
            "id": "3GICv7RT3x",
            "type": "list",
            "data": {
              "style": "ordered",
              "items": ["список 1", "список 2", "список 3"]
            }
          }
        ],
        "version": "2.22.2"
      },
      "id": 6
    },
    {
      "title": "Наикрутейший заголовок",
      "author": "Суперский автор",
      "source": "Супер секретный источник",
      "coverImage": "https://s1.1zoom.ru/big0/367/433183-Kysb.jpg",
      "description": "Lorem ipsum dolor sit amet, consectetur adipiscing elit. Integer vehicula lectus ut massa finibus interdum. Sed tincidunt felis eget purus pulvinar, at condimentum metus sodales. Praesent dictum commodo nunc, ut ornare metus gravida eget.",
      "content": {
        "time": 1634424774054,
        "blocks": [
          {
            "id": "Ik8uWoec7B",
            "type": "header",
            "data": {
              "text": "Заголовок",
              "level": 2
            }
          },
          {
            "id": "VggAl6ZV9M",
            "type": "paragraph",
            "data": {
              "text": "Текст текст текст"
            }
          },
          {
            "id": "3GICv7RT3x",
            "type": "list",
            "data": {
              "style": "ordered",
              "items": ["список 1", "список 2", "список 3"]
            }
          }
        ],
        "version": "2.22.2"
      },
      "id": 7
    },
    {
      "title": "Наикрутейший заголовок",
      "author": "Суперский автор",
      "source": "Супер секретный источник",
      "coverImage": "https://s1.1zoom.ru/big0/367/433183-Kysb.jpg",
      "description": "Lorem ipsum dolor sit amet, consectetur adipiscing elit. Integer vehicula lectus ut massa finibus interdum. Sed tincidunt felis eget purus pulvinar, at condimentum metus sodales. Praesent dictum commodo nunc, ut ornare metus gravida eget.",
      "content": {
        "time": 1634424774054,
        "blocks": [
          {
            "id": "Ik8uWoec7B",
            "type": "header",
            "data": {
              "text": "Заголовок",
              "level": 2
            }
          },
          {
            "id": "VggAl6ZV9M",
            "type": "paragraph",
            "data": {
              "text": "Текст текст текст"
            }
          },
          {
            "id": "3GICv7RT3x",
            "type": "list",
            "data": {
              "style": "ordered",
              "items": ["список 1", "список 2", "список 3"]
            }
          }
        ],
        "version": "2.22.2"
      },
      "id": 8
    },
    {
      "title": "Наикрутейший заголовок",
      "author": "Суперский автор",
      "source": "Супер секретный источник",
      "coverImage": "https://s1.1zoom.ru/big0/367/433183-Kysb.jpg",
      "description": "Lorem ipsum dolor sit amet, consectetur adipiscing elit. Integer vehicula lectus ut massa finibus interdum. Sed tincidunt felis eget purus pulvinar, at condimentum metus sodales. Praesent dictum commodo nunc, ut ornare metus gravida eget.",
      "content": {
        "time": 1634424774054,
        "blocks": [
          {
            "id": "Ik8uWoec7B",
            "type": "header",
            "data": {
              "text": "Заголовок",
              "level": 2
            }
          },
          {
            "id": "VggAl6ZV9M",
            "type": "paragraph",
            "data": {
              "text": "Текст текст текст"
            }
          },
          {
            "id": "3GICv7RT3x",
            "type": "list",
            "data": {
              "style": "ordered",
              "items": ["список 1", "список 2", "список 3"]
            }
          }
        ],
        "version": "2.22.2"
      },
      "id": 9
    },
    {
      "title": "Наикрутейший заголовок",
      "author": "Суперский автор",
      "source": "Супер секретный источник",
      "coverImage": "https://s1.1zoom.ru/big0/367/433183-Kysb.jpg",
      "description": "Lorem ipsum dolor sit amet, consectetur adipiscing elit. Integer vehicula lectus ut massa finibus interdum. Sed tincidunt felis eget purus pulvinar, at condimentum metus sodales. Praesent dictum commodo nunc, ut ornare metus gravida eget.",
      "content": {
        "time": 1634424774054,
        "blocks": [
          {
            "id": "Ik8uWoec7B",
            "type": "header",
            "data": {
              "text": "Заголовок",
              "level": 2
            }
          },
          {
            "id": "VggAl6ZV9M",
            "type": "paragraph",
            "data": {
              "text": "Текст текст текст"
            }
          },
          {
            "id": "3GICv7RT3x",
            "type": "list",
            "data": {
              "style": "ordered",
              "items": ["список 1", "список 2", "список 3"]
            }
          }
        ],
        "version": "2.22.2"
      },
      "id": 10
    },
    {
      "title": "Наикрутейший заголовок",
      "author": "Суперский автор",
      "source": "Супер секретный источник",
      "coverImage": "https://s1.1zoom.ru/big0/367/433183-Kysb.jpg",
      "description": "Lorem ipsum dolor sit amet, consectetur adipiscing elit. Integer vehicula lectus ut massa finibus interdum. Sed tincidunt felis eget purus pulvinar, at condimentum metus sodales. Praesent dictum commodo nunc, ut ornare metus gravida eget.",
      "content": {
        "time": 1634424774054,
        "blocks": [
          {
            "id": "Ik8uWoec7B",
            "type": "header",
            "data": {
              "text": "Заголовок",
              "level": 2
            }
          },
          {
            "id": "VggAl6ZV9M",
            "type": "paragraph",
            "data": {
              "text": "Текст текст текст"
            }
          },
          {
            "id": "3GICv7RT3x",
            "type": "list",
            "data": {
              "style": "ordered",
              "items": ["список 1", "список 2", "список 3"]
            }
          }
        ],
        "version": "2.22.2"
      },
      "id": 11
    },
    {
      "title": "Наикрутейший заголовок",
      "author": "Суперский автор",
      "source": "Супер секретный источник",
      "coverImage": "https://s1.1zoom.ru/big0/367/433183-Kysb.jpg",
      "description": "Lorem ipsum dolor sit amet, consectetur adipiscing elit. Integer vehicula lectus ut massa finibus interdum. Sed tincidunt felis eget purus pulvinar, at condimentum metus sodales. Praesent dictum commodo nunc, ut ornare metus gravida eget.",
      "content": {
        "time": 1634424774054,
        "blocks": [
          {
            "id": "Ik8uWoec7B",
            "type": "header",
            "data": {
              "text": "Заголовок",
              "level": 2
            }
          },
          {
            "id": "VggAl6ZV9M",
            "type": "paragraph",
            "data": {
              "text": "Текст текст текст"
            }
          },
          {
            "id": "3GICv7RT3x",
            "type": "list",
            "data": {
              "style": "ordered",
              "items": ["список 1", "список 2", "список 3"]
            }
          }
        ],
        "version": "2.22.2"
      },
      "id": 12
    },
    {
      "title": "Наикрутейший заголовок",
      "author": "Суперский автор",
      "source": "Супер секретный источник",
      "coverImage": "https://s1.1zoom.ru/big0/367/433183-Kysb.jpg",
      "description": "Lorem ipsum dolor sit amet, consectetur adipiscing elit. Integer vehicula lectus ut massa finibus interdum. Sed tincidunt felis eget purus pulvinar, at condimentum metus sodales. Praesent dictum commodo nunc, ut ornare metus gravida eget.",
      "content": {
        "time": 1634424774054,
        "blocks": [
          {
            "id": "Ik8uWoec7B",
            "type": "header",
            "data": {
              "text": "Заголовок",
              "level": 2
            }
          },
          {
            "id": "VggAl6ZV9M",
            "type": "paragraph",
            "data": {
              "text": "Текст текст текст"
            }
          },
          {
            "id": "3GICv7RT3x",
            "type": "list",
            "data": {
              "style": "ordered",
              "items": ["список 1", "список 2", "список 3"]
            }
          }
        ],
        "version": "2.22.2"
      },
      "id": 13
    },
    {
      "title": "Наикрутейший заголовок",
      "author": "Суперский автор",
      "source": "Супер секретный источник",
      "coverImage": "https://s1.1zoom.ru/big0/367/433183-Kysb.jpg",
      "description": "Lorem ipsum dolor sit amet, consectetur adipiscing elit. Integer vehicula lectus ut massa finibus interdum. Sed tincidunt felis eget purus pulvinar, at condimentum metus sodales. Praesent dictum commodo nunc, ut ornare metus gravida eget.",
      "content": {
        "time": 1634424774054,
        "blocks": [
          {
            "id": "Ik8uWoec7B",
            "type": "header",
            "data": {
              "text": "Заголовок",
              "level": 2
            }
          },
          {
            "id": "VggAl6ZV9M",
            "type": "paragraph",
            "data": {
              "text": "Текст текст текст"
            }
          },
          {
            "id": "3GICv7RT3x",
            "type": "list",
            "data": {
              "style": "ordered",
              "items": ["список 1", "список 2", "список 3"]
            }
          }
        ],
        "version": "2.22.2"
      },
      "id": 14
    },
    {
      "title": "Наикрутейший заголовок",
      "author": "Суперский автор",
      "source": "Супер секретный источник",
      "coverImage": "https://s1.1zoom.ru/big0/367/433183-Kysb.jpg",
      "description": "Lorem ipsum dolor sit amet, consectetur adipiscing elit. Integer vehicula lectus ut massa finibus interdum. Sed tincidunt felis eget purus pulvinar, at condimentum metus sodales. Praesent dictum commodo nunc, ut ornare metus gravida eget.",
      "content": {
        "time": 1634424774054,
        "blocks": [
          {
            "id": "Ik8uWoec7B",
            "type": "header",
            "data": {
              "text": "Заголовок",
              "level": 2
            }
          },
          {
            "id": "VggAl6ZV9M",
            "type": "paragraph",
            "data": {
              "text": "Текст текст текст"
            }
          },
          {
            "id": "3GICv7RT3x",
            "type": "list",
            "data": {
              "style": "ordered",
              "items": ["список 1", "список 2", "список 3"]
            }
          }
        ],
        "version": "2.22.2"
      },
      "id": 15
    },
    {
      "title": "Наикрутейший заголовок",
      "author": "Суперский автор",
      "source": "Супер секретный источник",
      "coverImage": "https://s1.1zoom.ru/big0/367/433183-Kysb.jpg",
      "description": "Lorem ipsum dolor sit amet, consectetur adipiscing elit. Integer vehicula lectus ut massa finibus interdum. Sed tincidunt felis eget purus pulvinar, at condimentum metus sodales. Praesent dictum commodo nunc, ut ornare metus gravida eget.",
      "content": {
        "time": 1634424774054,
        "blocks": [
          {
            "id": "Ik8uWoec7B",
            "type": "header",
            "data": {
              "text": "Заголовок",
              "level": 2
            }
          },
          {
            "id": "VggAl6ZV9M",
            "type": "paragraph",
            "data": {
              "text": "Текст текст текст"
            }
          },
          {
            "id": "3GICv7RT3x",
            "type": "list",
            "data": {
              "style": "ordered",
              "items": ["список 1", "список 2", "список 3"]
            }
          }
        ],
        "version": "2.22.2"
      },
      "id": 16
    }
  ],
  "users": [
    {
      "id": 1,
      "login": "admin",
      "password": "pa$$word"
    },
    {
      "id": 2,
      "login": "parker",
      "password": "root666"
    }
  ],
  "tokens": [
    "IzRH1BdRCZ4VUlIYV9eriUlRCxpreTPFGzD9FaqFr44A5iMZCGSIEuk8KsTfWGxgILzMdNZp2999eGElFlDLWodT3Apv9xTj55MZ",
    "tAPKP1oQVlMc1Q0VVEEpr4cuRNjh3buXLQaBc75WtvA60m1s37p7JLgoh2ye5pMEsdryBG7fYxsg1taWpZKScA5xXPEVfuS3WpAU",
    "bVMtHVNU12tt9mEcLE2TR8HeqRYHOJKTK9UHRD4by6uEqKgS0jkdeXlyHImVLpBVJV0o8ZWJnX1uG3OypzfsieBtK3MqfE0CQZs4",
    "R3l9E1Cvi6ykPbmnPzAmZwdC4nhsYTLi2baRUNNzUwFHGVzOI8iDKyriBdF6s48PCEKbUaSmiT1rLyNi7m2usPDj2KrYAGb856fz",
    "GuZSRVsYsrM8Z6iS5JiDYSQUpLzmPWqVmKc8nPF94Xt0QQNf7zpmYsu3DQhBsNVplCPmOEcMoMTjYofjTVvHJQdmKU8H4eOzR9dj",
    "PUljIBKD9M92y0KlJ9YY6KggGChuxE72QTcERqytXml0DSZGCIK5txNAMeDkaptaGjezV9oVtG4aUCE17OxSsxrwLy8IMlbT4UH8",
    "IjDZZxbQLtyniQkADVmmZ1xMrsCr9eHhnCUe3tK2xFsVceH4tk0rfOplq3nFkW2SBP43KQaggGrAsJ3AMYHr3rg64FmOIeqR11ar",
    "cnjcWIFUfHcxqpJci7XMDcIgq9F2vwWuDUL5QymFwIG7W4oT3nqkHATJuRSqu2cBslRiBmsCdyGvTdy239WMxaMKjff36dkT8eOx",
    "IkTFXnCE6KG1CKpwT5X7xLR0iCQqFHZVugtQfucZhJsMGosVh5XoU4LrK54HgUjCHioIxfvZq4pU2xk7CLOwFRLxIxj0kS17YkJ3",
    "AbSE405j9DdOyinMJs5X43gyTBm4JCjaC8jwCuT32bwjwB0EZQP7VW66HvneRFLXgEAC7c5vy3tStlEC9L3UMZtftqmPI3PdYIM5",
    "6YE61rHutrjxUceleRrAL1Jl4r8vYY2ok8jMX3C5Hr9MOCoPrCd3Qdmwlsgdo3olTReF7CkpK8jJoeB5PLRQbnjI6vhoC17b0VAE",
    "zDZLG0O4rbNrNpKfKPFgluJYtJcXa3AWpcRkbWztp0fA7VT5tTn2DZiVCiTTyKVTsbZk8vYWIamks6LiUVK8rU7pPYKZC0qfzEQ1",
    "A5Z2edG1S9j9Co0ykzO4UY6ztNEJtC6QWvIX6TuCLEsrfAbrTDZgWEyCwGrMjZkP3USD5ku2EwCY4P3bH8x8tDYc89ndH0YF6Uvc",
    "EvJyFwR4Kzq1it9TIDyaUy1xV9zbGukzfDS22qKPKwpogTgoUImyAt1rXHyJBmXzkFkVdixNVFHXiRYuYCrV7wE8vpFQB4VJLgG4",
    "iVJXUwTPX0x9x5fxKxIn9ahItaYjh7YFSVWFSwxRfWoEs9EpGYRhN4jiiodgTHjyjJ4H1RLTPVwh6vWRGh6NfzgNW8tszFytBoDa",
    "Kz6mMQVPNnK6ZoZM3CG7Vn4O3JuGdcbow51AeX8n3mrdg2TnRGHeXupWQQonPWkoL7gah2diLMnnX9KT7nFLgpvncFdePLyf9LOm",
    "LnTp49ldsKRZ4jm4ecC0cvljoHY351M8aMjUWqj8jF3FrTATkhGDTCM7nz0dmWolxZe0igXn52i8lTW37xCk5vjpL1wMLKT9OYDo",
    "ykuBWU8iz5M8cULxeomNIk72PQULJZ3W45R5VuJmX730oTZkwmvbAr4XkY7m3u73calpfEz2Ym3MNIOUAN3G2GUGTt6PnDTJKK2G",
    "uobKVZsjq4JsqTAqnu7VDgzYQAWGztQyo9J4EIc1hp3JZUxLN1KJVvee2FG5Ufqi92vYrajhewAXcJ6ZcBT8sHIHCodWVWxC407k",
    "Hx86wlcvdRVKigHfUyAk9JCFjFRgqf2r6m3Xs9HwE0McLCwN1yI2MMJinaMr2mLDtmbAbN2amS4PUKywXiZDfrpzM7VxgFAs5Qfk",
    "HtsFG0uZHPvKZU8PBDI5E0ymlljeg8cUhtIAR47R44HYw5TO7hSYwWweqG5r0Di1qTOyahSMp7f4NSwkzdRl4hwxZbZesf9BdoKQ",
    "vpFxFxnFf7o4KG50HgiUwktibzWwzPJK8NT6rN0TzcE1DGFmrZgq5cD370H614PdYNe9N7lB73zqR5yoWfDn4EXvo2lN4Emi7ye2",
    "LEcpdTU12oMDT8llsr1A4nk3LFHBmnhgt6ShCvOV4pcoOQPPrc7HqfcrkaS4di1xsjpGHD3ttPHC2AaaCWQcRcb42bCXXDTQMCiL",
    "4aQOPIVutqNCX0CYlIMhODUUX1h9ziOZEHzvgiZyXbqo5YfN3lAKtCsljVpUpl4PXUfukPcvNoC4kzjRtv2fOmZT7OVSD8HGTkOV",
    "X5LRchr5wqhnXw54HQHuHTD8RgwhlFtTGNaO7fhKJZt0yeFbLuWzLH9UqNIyHQdZJNxfTl7WmIPy7WZbIvs63kqV5ki0NkYwLcDD",
    "BxRLjP0IFk7b7k9ahpxswJad1OgvNzypfWNCxCo78Z1MriC97AOqsJSr7oFG2GEu6jWYRmVjyJ6oUNsSP1RyrowAGdfK9HG4ufmp",
    "brsfjOAPHJh4fIiRO2VL1SBlg7VrvDGDubQO96wH2fNNjp5NPG5Omzz9iruBdAYhDVjfauauwY6lcazgIcyysvxsywRuS7O0sZt4",
    "67rwi2PnK8G0buPlPYEefMPAZKVXdYtmNsNRoYLoJvGfb7dBR03sSg2ZFlHNzutS4QrXpXPZ20AYLjrJTCDNN81aS0c6pSQU8xiU",
    "hP3SZzuMzpUHx4iAi12VfLmXmbL8WQLF50dwAFWpsGBX9984vWQrdyEaxZPVuU8ddgrIqCCYoBno0IybaQNkMXogra35fd3ZeenT",
    "nIKm92dK6DKjpf5GQT1nusu97hxsDxoL2JzK9uvEHcvRm5z9rcHBicxQskpYpZJgbhKIyQiN8btGnAuEISZUkspVSYuPWJjfwKow",
    "eGZbbWMKGcLJGjzU4YQpEEsE91MGllrqTi96iEwhwPR2UZzLbLEMnNZxLKzQr6HEjFCLP9IbFlPuxjEP5B8MPuluMhBdhuhrQJyE",
    "HyPsC4KXH2qAsgwnSF7PUUS2kk7qywmHbttSPu206oSNRRFSrgDjGltAlXijhtnDZHMxRl8v08vFJhws8yUWo4630nSH8AIvJGQo",
    "qKulAUN0Bu14C1RCAa0KBwa8jqlQ6A98HvM5gsI92T1JytbQNO0Q03tuiTMdI01B7Ph1UeFDPzOowVNwctRQDZtAhqbuzgqFLgtZ",
    "8Cijnh9mdwAhQnRuICrbIhmEULg5G06HsLmJqnDG1u1CTBQV37qHpObrjIQVFRtcIiRYo34xM8G6QErVhN2kpnd6iDIh2sfDZDmW"
  ]
}
